odoo/addons/account_invoice_select_for_payment/README.rst
odoo/addons/account_invoice_select_for_payment/__init__.py
odoo/addons/account_invoice_select_for_payment/__manifest__.py
odoo/addons/account_invoice_select_for_payment/i18n/account_invoice_select_for_payment.pot
odoo/addons/account_invoice_select_for_payment/i18n/fr.po
odoo/addons/account_invoice_select_for_payment/models/__init__.py
odoo/addons/account_invoice_select_for_payment/models/account_move.py
odoo/addons/account_invoice_select_for_payment/models/account_payment.py
odoo/addons/account_invoice_select_for_payment/readme/CONTRIBUTORS.rst
odoo/addons/account_invoice_select_for_payment/readme/DESCRIPTION.rst
odoo/addons/account_invoice_select_for_payment/readme/USAGE.rst
odoo/addons/account_invoice_select_for_payment/static/description/icon.png
odoo/addons/account_invoice_select_for_payment/static/description/index.html
odoo/addons/account_invoice_select_for_payment/views/account_move.xml
odoo13_addon_account_invoice_select_for_payment-13.0.1.0.1.dev6.dist-info/METADATA
odoo13_addon_account_invoice_select_for_payment-13.0.1.0.1.dev6.dist-info/WHEEL
odoo13_addon_account_invoice_select_for_payment-13.0.1.0.1.dev6.dist-info/top_level.txt
odoo13_addon_account_invoice_select_for_payment-13.0.1.0.1.dev6.dist-info/RECORD
