Metadata-Version: 2.1
Name: odoo13-addon-account_invoice_select_for_payment
Version: 13.0.1.0.1.dev6
Summary: Account Invoice Select for Payment
Home-page: https://github.com/OCA/bank-payment
Author: Camptocamp,Odoo Community Association (OCA)
Author-email: support@odoo-community.org
License: AGPL-3
Classifier: Programming Language :: Python
Classifier: Framework :: Odoo
Classifier: Framework :: Odoo :: 13.0
Classifier: License :: OSI Approved :: GNU Affero General Public License v3
Classifier: Development Status :: 3 - Alpha
Requires-Python: >=3.5
Requires-Dist: odoo <13.1dev,>=13.0a
